__init__.py
api/__init__.py
api/main.py
api/middleware/__init__.py
api/middleware/error_handler.py
api/middleware/logging_middleware.py
api/middleware/rate_limit.py
api/middleware/request_id.py
api/models/__init__.py
api/models/request.py
api/models/response.py
api/routes/__init__.py
api/routes/analytics.py
api/routes/api_keys.py
api/routes/auth.py
api/routes/batch.py
api/routes/cache.py
api/routes/chart_templates.py
api/routes/comparison.py
api/routes/compression.py
api/routes/cost_tracking.py
api/routes/dashboards.py
api/routes/discovery.py
api/routes/export.py
api/routes/export_templates.py
api/routes/health.py
api/routes/history.py
api/routes/indexing.py
api/routes/management.py
api/routes/metrics.py
api/routes/optimization.py
api/routes/pagination.py
api/routes/pool_management.py
api/routes/query.py
api/routes/scheduled_exports.py
api/routes/scheduler.py
api/routes/sharing.py
api/routes/stats.py
api/routes/templates.py
api/routes/transformation.py
api/routes/versioning.py
api/routes/visualization.py
api/routes/webhooks.py
api/routes/websocket.py
application/__init__.py
application/services/__init__.py
application/services/advanced_visualization_service.py
application/services/batch_query_service.py
application/services/chart_template_service.py
application/services/dashboard_service.py
application/services/discovery_service.py
application/services/export_template_service.py
application/services/hybrid_query_router.py
application/services/indexing_service.py
application/services/pagination_service.py
application/services/query_comparison_service.py
application/services/query_service.py
application/services/query_template_service.py
application/services/scheduled_export_service.py
application/services/scheduler_service.py
application/services/transformation_service.py
application/services/visualization_service.py
cli/__init__.py
cli/main.py
core/__init__.py
core/constants.py
core/exceptions.py
domain/__init__.py
domain/database.py
domain/export_template.py
the_discoverer-1.0.1.dist-info/LICENSE
the_discoverer-1.0.1.dist-info/METADATA
the_discoverer-1.0.1.dist-info/WHEEL
the_discoverer-1.0.1.dist-info/entry_points.txt
the_discoverer-1.0.1.dist-info/top_level.txt
the_discoverer-1.0.1.dist-info/RECORD
