Metadata-Version: 2.1
Name: the-discoverer
Version: 1.0.1
Summary: AI-powered database discovery and query agent
Author: Malek Khannoussi
Maintainer: Malek Khannoussi
Project-URL: Homepage, https://github.com/khannoussi-malek/the-discoverer
Project-URL: Repository, https://github.com/khannoussi-malek/the-discoverer
Project-URL: Documentation, https://github.com/khannoussi-malek/the-discoverer
Project-URL: Issues, https://github.com/khannoussi-malek/the-discoverer/issues
Project-URL: LinkedIn, https://www.linkedin.com/in/khannoussi-malek/
Keywords: database,discovery,query,ai,llm,sql,nosql,vector-database,qdrant,postgresql,mysql,mongodb,fastapi,data-visualization
Classifier: Development Status :: 4 - Beta
Classifier: Intended Audience :: Developers
Classifier: License :: OSI Approved :: MIT License
Classifier: Programming Language :: Python :: 3
Classifier: Programming Language :: Python :: 3.10
Classifier: Programming Language :: Python :: 3.11
Classifier: Programming Language :: Python :: 3.12
Classifier: Topic :: Database
Classifier: Topic :: Software Development :: Libraries :: Python Modules
Classifier: Topic :: Scientific/Engineering :: Artificial Intelligence
Requires-Python: >=3.10
License-File: LICENSE
Requires-Dist: fastapi>=0.104.1
Requires-Dist: uvicorn[standard]>=0.24.0
Requires-Dist: pydantic>=2.5.0
Requires-Dist: pydantic-settings>=2.1.0
Requires-Dist: python-dotenv>=1.0.0
Requires-Dist: click>=8.1.0
Requires-Dist: httpx>=0.25.2
Requires-Dist: asyncpg>=0.29.0
Requires-Dist: aiomysql>=0.2.0
Requires-Dist: motor>=3.3.2
Requires-Dist: cassandra-driver>=3.29.0
Requires-Dist: elasticsearch>=8.11.0
Requires-Dist: sqlalchemy>=2.0.23
Requires-Dist: qdrant-client>=1.7.0
Requires-Dist: sentence-transformers>=2.2.2
Requires-Dist: openai>=1.3.7
Requires-Dist: langchain>=0.0.350
Requires-Dist: langchain-openai>=0.0.2
Requires-Dist: redis>=5.0.1
Requires-Dist: cachetools>=5.3.2
Requires-Dist: plotly>=5.18.0
Requires-Dist: pandas>=2.1.4
Requires-Dist: numpy>=1.26.2
Requires-Dist: openpyxl>=3.1.2
Requires-Dist: kaleido>=0.2.1
Requires-Dist: pyarrow>=14.0.1
Requires-Dist: fastavro>=1.8.2
Requires-Dist: aiohttp>=3.9.1
Requires-Dist: pyyaml>=6.0.1
Requires-Dist: aiosqlite>=0.19.0
Requires-Dist: pyjwt>=2.8.0
Requires-Dist: prometheus-client>=0.19.0
Provides-Extra: dev
Requires-Dist: pytest>=7.4.3; extra == "dev"
Requires-Dist: pytest-asyncio>=0.21.1; extra == "dev"
Requires-Dist: pytest-cov>=4.1.0; extra == "dev"
Requires-Dist: pytest-mock>=3.12.0; extra == "dev"
Requires-Dist: black>=23.11.0; extra == "dev"
Requires-Dist: flake8>=6.1.0; extra == "dev"
Requires-Dist: mypy>=1.7.1; extra == "dev"
